inventree_apprise/ApprisePlugin.py
inventree_apprise/__init__.py
inventree_apprise-1.2.dist-info/licenses/LICENSE
inventree_apprise-1.2.dist-info/METADATA
inventree_apprise-1.2.dist-info/WHEEL
inventree_apprise-1.2.dist-info/entry_points.txt
inventree_apprise-1.2.dist-info/top_level.txt
inventree_apprise-1.2.dist-info/RECORD
